psstdata/__init__.py
psstdata/__main__.py
psstdata/_system.py
psstdata/config.py
psstdata/consts.py
psstdata/datastructures.py
psstdata/downloading.py
psstdata/loading.py
psstdata/logs.py
psstdata/networking.py
psstdata/tasks.py
psstdata/versioning.py
psstdata/artificialdata/versions.json
psstdata/artificialdata/psst-data-ARTIFICIAL/test/asr_test.tsv
psstdata/artificialdata/psst-data-ARTIFICIAL/test/correctness_test.tsv
psstdata/artificialdata/psst-data-ARTIFICIAL/test/audio/empty.wav
psstdata/artificialdata/psst-data-ARTIFICIAL/train/asr_train.tsv
psstdata/artificialdata/psst-data-ARTIFICIAL/train/correctness_train.tsv
psstdata/artificialdata/psst-data-ARTIFICIAL/train/audio/empty.wav
psstdata/artificialdata/psst-data-ARTIFICIAL/valid/asr_valid.tsv
psstdata/artificialdata/psst-data-ARTIFICIAL/valid/correctness_valid.tsv
psstdata/artificialdata/psst-data-ARTIFICIAL/valid/audio/empty.wav
psstdata/assets/__init__.py
psstdata/assets/correctness.json
psstdata/assets/vocab_arpabet.json
psstdata-1.0.1.dist-info/METADATA
psstdata-1.0.1.dist-info/WHEEL
psstdata-1.0.1.dist-info/top_level.txt
psstdata-1.0.1.dist-info/RECORD
