Metadata-Version: 2.1
Name: psstdata
Version: 1.0.1
Summary: Tool for downloading and loading the data for the PSST Challenge
Home-page: https://github.com/PSST-Challenge/psstdata
Author: Portland Allied Labs for Aphasia Technology (PALAT)
Author-email: galer@ohsu.edu
License: UNKNOWN
Platform: UNKNOWN
Requires-Dist: requests
